{
  "schemaVersion": 1,
  "id": "pickblockstate",
  "version": "${version}",

  "name": "Pick-BlockState",
  "description": "Pick-block now copies the blockstate if the block isn't a block entity",
  "authors": [
    "Minenash"
  ],
  "contact": {
    "sources": "https://github.com/FabricMC/fabric-example-mod"
  },

  "license": "MIT",
  "icon": "assets/modid/icon.png",

  "environment": "client",
  "mixins": [
    "pickblockstate.mixins.json"
  ],

  "depends": {
    "fabric": "*",
    "minecraft": "1.16.x"
  }
}
